fontmake/__init__.py
fontmake/__main__.py
fontmake/_version.py
fontmake/compatibility.py
fontmake/errors.py
fontmake/font_project.py
fontmake/instantiator.py
fontmake/ttfautohint.py
fontmake-3.10.0.dist-info/LICENSE
fontmake-3.10.0.dist-info/METADATA
fontmake-3.10.0.dist-info/WHEEL
fontmake-3.10.0.dist-info/entry_points.txt
fontmake-3.10.0.dist-info/top_level.txt
fontmake-3.10.0.dist-info/RECORD
