Metadata-Version: 2.1
Name: fontmake
Version: 3.10.0
Summary: Compile fonts from sources (UFO, Glyphs) to binary (OpenType, TrueType).
Home-page: https://github.com/googlei18n/fontmake
Author: James Godfrey-kittle
Maintainer: Cosimo Lupo
Maintainer-email: cosimo@anthrotype.com
License: Apache Software License 2.0
Classifier: Development Status :: 4 - Beta
Classifier: Environment :: Console
Classifier: Intended Audience :: Developers
Classifier: License :: OSI Approved :: Apache Software License
Classifier: Natural Language :: English
Classifier: Operating System :: OS Independent
Classifier: Programming Language :: Python
Classifier: Programming Language :: Python :: 3
Classifier: Topic :: Multimedia :: Graphics
Classifier: Topic :: Multimedia :: Graphics :: Graphics Conversion
Classifier: Topic :: Multimedia :: Graphics :: Editors :: Vector-Based
Classifier: Topic :: Text Processing :: Fonts
Requires-Python: >=3.8
License-File: LICENSE
Requires-Dist: fontMath>=0.9.4
Requires-Dist: glyphsLib>=6.9.2
Requires-Dist: ufoLib2>=0.16.0
Requires-Dist: fonttools[lxml,ufo,unicode]>=4.54.1; implementation_name == "cpython"
Requires-Dist: fonttools[ufo,unicode]>=4.54.1; implementation_name != "cpython"
Requires-Dist: ufo2ft[compreffor]>=3.3.1
Provides-Extra: pathops
Requires-Dist: skia-pathops>=0.3.0; extra == "pathops"
Provides-Extra: lxml
Provides-Extra: mutatormath
Provides-Extra: autohint
Requires-Dist: ttfautohint-py>=0.5.0; extra == "autohint"
Provides-Extra: json
Requires-Dist: ufoLib2[json]>=0.16.0; extra == "json"
Provides-Extra: repacker
Requires-Dist: fonttools[lxml,repacker,ufo,unicode]>=4.54.1; implementation_name == "cpython" and extra == "repacker"
Requires-Dist: fonttools[repacker,ufo,unicode]>=4.54.1; implementation_name != "cpython" and extra == "repacker"
Provides-Extra: all
Requires-Dist: skia-pathops>=0.3.0; extra == "all"
Requires-Dist: ttfautohint-py>=0.5.0; extra == "all"
Requires-Dist: ufoLib2[json]>=0.16.0; extra == "all"
Requires-Dist: fonttools[lxml,repacker,ufo,unicode]>=4.54.1; implementation_name == "cpython" and extra == "all"
Requires-Dist: fonttools[repacker,ufo,unicode]>=4.54.1; implementation_name != "cpython" and extra == "all"
